pytest_jobserver/__init__.py
pytest_jobserver/configure.py
pytest_jobserver/metadata.py
pytest_jobserver/plugin.py
pytest_jobserver/system.py
pytest_jobserver/test/__init__.py
pytest_jobserver/test/jobserver.py
pytest_jobserver/test/test_plugin.py
pytest_jobserver/test/test_system.py
pytest_jobserver-1.0.0.dist-info/LICENSE
pytest_jobserver-1.0.0.dist-info/METADATA
pytest_jobserver-1.0.0.dist-info/WHEEL
pytest_jobserver-1.0.0.dist-info/entry_points.txt
pytest_jobserver-1.0.0.dist-info/top_level.txt
pytest_jobserver-1.0.0.dist-info/RECORD
