Metadata-Version: 2.1
Name: pytest-jobserver
Version: 1.0.0
Summary: Limit parallel tests with posix jobserver.
Home-page: https://github.com/tommilligan/pytest-jobserver
Author: Tom Milligan
Author-email: code@tommilligan.net
Maintainer: Tom Milligan
Maintainer-email: code@tommilligan.net
License: Apache Software License 2.0
Keywords: pytest jobserver posix make cargo limit cap parallel limit
Platform: UNKNOWN
Classifier: Development Status :: 5 - Production/Stable
Classifier: Framework :: Pytest
Classifier: Intended Audience :: Developers
Classifier: Topic :: Software Development :: Testing
Classifier: Programming Language :: Python
Classifier: Programming Language :: Python :: 3
Classifier: Programming Language :: Python :: 3.6
Classifier: Programming Language :: Python :: 3.7
Classifier: Programming Language :: Python :: Implementation :: CPython
Classifier: Operating System :: POSIX
Classifier: Operating System :: POSIX :: Linux
Classifier: License :: OSI Approved :: Apache Software License
Requires-Python: >=3.4
Requires-Dist: pytest
